iokit/__init__.py
iokit/checksum.py
iokit/py.typed
iokit/state.py
iokit/extensions/__init__.py
iokit/extensions/audio.py
iokit/extensions/auto.py
iokit/extensions/dat.py
iokit/extensions/enc.py
iokit/extensions/env.py
iokit/extensions/gz.py
iokit/extensions/image.py
iokit/extensions/json.py
iokit/extensions/jsonl.py
iokit/extensions/npy.py
iokit/extensions/table.py
iokit/extensions/tar.py
iokit/extensions/txt.py
iokit/extensions/yaml.py
iokit/extensions/zip.py
iokit/storage/__init__.py
iokit/storage/local.py
iokit/storage/storage.py
iokit/storage/web.py
iokit/tools/__init__.py
iokit/tools/time.py
iokit-0.3.4.dist-info/licenses/LICENSE
iokit-0.3.4.dist-info/METADATA
iokit-0.3.4.dist-info/WHEEL
iokit-0.3.4.dist-info/top_level.txt
iokit-0.3.4.dist-info/RECORD
