Metadata-Version: 2.4
Name: iokit
Version: 0.3.4
Summary: Input Output Kit
Author-email: "Vladislav A. Proskurov" <rilshok@pm.me>
License: MIT
Project-URL: Homepage, https://github.com/rilshok/iokit
Project-URL: Repository, https://github.com/rilshok/iokit.git
Project-URL: Issues, https://github.com/rilshok/iokit/issues
Requires-Python: >=3.10
License-File: LICENSE
Requires-Dist: humanize>=4.9.0
Requires-Dist: jsonlines>=4.0.0
Requires-Dist: python-dateutil>=2.8.2
Requires-Dist: python-dotenv>=1.0.1
Requires-Dist: PyYAML>=6.0.1
Requires-Dist: pytz>=2024.1
Requires-Dist: requests>=2.32.3
Requires-Dist: typing-extensions>=4.8.0
Requires-Dist: cryptography>=41.0.7
Requires-Dist: numpy>=1.21.1
Requires-Dist: soundfile>=0.12.1
Requires-Dist: pandas>=1.5.3
Requires-Dist: Pillow>=10.4.0
Requires-Dist: xxhash>=3.4.1
Provides-Extra: dev
Requires-Dist: iokit[lint,test]; extra == "dev"
Provides-Extra: lint
Requires-Dist: mypy>=1.7.1; extra == "lint"
Requires-Dist: ruff>=0.6.3; extra == "lint"
Requires-Dist: types-pytz>=2024.1; extra == "lint"
Requires-Dist: types-requests>=2.31.0; extra == "lint"
Requires-Dist: types-PyYAML>=6.0.12; extra == "lint"
Requires-Dist: types-python-dateutil>=2.8.19; extra == "lint"
Provides-Extra: test
Requires-Dist: pytest>=8.2.2; extra == "test"
Requires-Dist: pytest-cov==6.0.0; extra == "test"
Requires-Dist: pytest-xdist>=3.6.1; extra == "test"
Dynamic: license-file
